{
  "id": "evt_1773067910",
  "recipient": "valentine",
  "sender": "EnvMonitor",
  "type": "event_notification",
  "content": {
    "title": "SECTOR_1_HEARTBEAT",
    "description": "Vitals: RAM:1643MB, CPU:66.7%, Heat:48\u00b0C",
    "payload": {
      "timestamp": "2026-03-09T11:51:50.618956",
      "health_category": "NOMINAL",
      "top_cpu": "66.7%",
      "ram_mb": 1643,
      "swap_percent": 88.0,
      "helper_count": 20,
      "thermal_proxy": "48\u00b0C"
    }
  },
  "metadata": {
    "timestamp": "2026-03-09T11:51:50.630984",
    "priority": 3
  }
}