{
  "id": "evt_1773071119",
  "recipient": "valentine",
  "sender": "EnvMonitor",
  "type": "event_notification",
  "content": {
    "title": "SECTOR_1_HEARTBEAT",
    "description": "Vitals: RAM:1964MB, CPU:72.5%, Heat:47\u00b0C",
    "payload": {
      "timestamp": "2026-03-09T12:45:19.142393",
      "health_category": "NOMINAL",
      "top_cpu": "72.5%",
      "ram_mb": 1964,
      "swap_percent": 88.8,
      "helper_count": 20,
      "thermal_proxy": "47\u00b0C"
    }
  },
  "metadata": {
    "timestamp": "2026-03-09T12:45:19.154315",
    "priority": 3
  }
}