{
  "id": "evt_1773069376",
  "recipient": "valentine",
  "sender": "EnvMonitor",
  "type": "event_notification",
  "content": {
    "title": "SECTOR_1_HEARTBEAT",
    "description": "Vitals: RAM:2225MB, CPU:69.2%, Heat:46\u00b0C",
    "payload": {
      "timestamp": "2026-03-09T12:16:16.772031",
      "health_category": "NOMINAL",
      "top_cpu": "69.2%",
      "ram_mb": 2225,
      "swap_percent": 75.2,
      "helper_count": 20,
      "thermal_proxy": "46\u00b0C"
    }
  },
  "metadata": {
    "timestamp": "2026-03-09T12:16:16.780764",
    "priority": 3
  }
}