{
  "id": "evt_1773067161",
  "recipient": "valentine",
  "sender": "EnvMonitor",
  "type": "event_notification",
  "content": {
    "title": "SECTOR_1_HEARTBEAT",
    "description": "Vitals: RAM:2435MB, CPU:28.8%, Heat:46\u00b0C",
    "payload": {
      "timestamp": "2026-03-09T11:39:21.527377",
      "health_category": "NOMINAL",
      "top_cpu": "28.8%",
      "ram_mb": 2435,
      "swap_percent": 78.4,
      "helper_count": 20,
      "thermal_proxy": "46\u00b0C"
    }
  },
  "metadata": {
    "timestamp": "2026-03-09T11:39:21.527920",
    "priority": 3
  }
}